ansi2txt.py
ansi2txt-0.2.0.dist-info/LICENSE
ansi2txt-0.2.0.dist-info/METADATA
ansi2txt-0.2.0.dist-info/WHEEL
ansi2txt-0.2.0.dist-info/entry_points.txt
ansi2txt-0.2.0.dist-info/RECORD
